pyminiscraper/__init__.py
pyminiscraper/atom.py
pyminiscraper/config.py
pyminiscraper/context.py
pyminiscraper/deque.py
pyminiscraper/domain_metadata.py
pyminiscraper/extract.py
pyminiscraper/feed.py
pyminiscraper/filter.py
pyminiscraper/hash.py
pyminiscraper/html.py
pyminiscraper/main_rss.py
pyminiscraper/main_scheduling.py
pyminiscraper/main_sitemap.py
pyminiscraper/main_web.py
pyminiscraper/metadata.py
pyminiscraper/model.py
pyminiscraper/py.typed
pyminiscraper/ratelimiter.py
pyminiscraper/robots.py
pyminiscraper/rss.py
pyminiscraper/scrape_html_browser.py
pyminiscraper/scrape_html_http.py
pyminiscraper/scraper.py
pyminiscraper/sitemap.py
pyminiscraper/stats.py
pyminiscraper/store_file.py
pyminiscraper/store_memory.py
pyminiscraper/text.py
pyminiscraper/url.py
pyminiscraper-2.0.2.dist-info/METADATA
pyminiscraper-2.0.2.dist-info/WHEEL
pyminiscraper-2.0.2.dist-info/top_level.txt
pyminiscraper-2.0.2.dist-info/RECORD
