Metadata-Version: 2.2
Name: pyminiscraper
Version: 2.0.2
Summary: A mini web scraping utility package
Author-email: Timur Valiulin <timurua@gmail.com>
License: MIT
Project-URL: Homepage, https://github.com/timurua/pyminiscraper
Classifier: Programming Language :: Python :: 3
Classifier: License :: OSI Approved :: MIT License
Classifier: Operating System :: OS Independent
Requires-Python: >=3.10
Requires-Dist: beautifulsoup4>=4.12.2
Requires-Dist: requests>=2.31.0
Requires-Dist: lxml>=4.9.3
Requires-Dist: selenium>=4.11.2
Requires-Dist: python-dotenv>=1.0.0
Requires-Dist: urllib3>=2.0.4
Requires-Dist: click>=8.1.8
Requires-Dist: aiohttp>=3.11.11
Requires-Dist: extruct>=0.18.0
Requires-Dist: python-dateutil>=2.9.0
Requires-Dist: aiolimiter>=1.2.1
Requires-Dist: types-beautifulsoup4>=4.12.0
Requires-Dist: types-python-dateutil>=2.9.0
